malayalam_morpheme_splitter/__init__.py
malayalam_morpheme_splitter/db_interface.py
malayalam_morpheme_splitter/data/__init__.py
malayalam_morpheme_splitter/data/malayalam_words.py
malayalam_morpheme_splitter/data/morph_examples.py
malayalam_morpheme_splitter-1.0.0b2.dist-info/LICENSE.txt
malayalam_morpheme_splitter-1.0.0b2.dist-info/METADATA
malayalam_morpheme_splitter-1.0.0b2.dist-info/WHEEL
malayalam_morpheme_splitter-1.0.0b2.dist-info/entry_points.txt
malayalam_morpheme_splitter-1.0.0b2.dist-info/top_level.txt
malayalam_morpheme_splitter-1.0.0b2.dist-info/RECORD
