Metadata-Version: 2.1
Name: malayalam_morpheme_splitter
Version: 1.0.0b2
Summary: An example based approach at separating suffixes in Malayalam text.
Author: BCS Team
Author-email: Kavitha.Raju@bridgeconn.com, gladysann1307@gmail.com
License: MIT
Project-URL: Source Repository, https://github.com/kavitharaju/Malayalam-Morpheme-Splitter
License-File: LICENSE.txt
